deep_space_trader/__init__.py
deep_space_trader/__main__.py
deep_space_trader/config.py
deep_space_trader/constants.py
deep_space_trader/game_state.py
deep_space_trader/high_scores.py
deep_space_trader/information_bar.py
deep_space_trader/item_browsers.py
deep_space_trader/item_prices.py
deep_space_trader/items.py
deep_space_trader/location_browser.py
deep_space_trader/location_picker.py
deep_space_trader/main_widget.py
deep_space_trader/planet.py
deep_space_trader/planet_image.py
deep_space_trader/price_graph.py
deep_space_trader/store.py
deep_space_trader/top_button_bar.py
deep_space_trader/transaction_dialogs.py
deep_space_trader/utils.py
deep_space_trader/images/icon.ico
deep_space_trader/images/icon.png
deep_space_trader/images/planet_background.png
deep_space_trader/images/planet_fill.png
deep_space_trader/images/planet_layers.xcf
deep_space_trader/images/planet_outline.png
deep_space_trader/images/planet_ring.png
deep_space_trader/images/planet_shine.png
deep_space_trader/images/planet_shine_1.png
deep_space_trader/images/planet_shine_2.png
deep_space_trader/images/planet_shine_3.png
deep_space_trader/images/planet_shine_4.png
deep_space_trader-1.3.1.dist-info/LICENSE
deep_space_trader-1.3.1.dist-info/METADATA
deep_space_trader-1.3.1.dist-info/WHEEL
deep_space_trader-1.3.1.dist-info/top_level.txt
deep_space_trader-1.3.1.dist-info/RECORD
