Metadata-Version: 2.1
Name: deep-space-trader
Version: 1.3.1
Summary: Dumb space game
Home-page: http://github.com/eriknyquist/deep_space_trader
Author: Erik Nyquist
Author-email: eknyquist@gmail.com
License: Apache 2.0
Platform: UNKNOWN
Requires-Dist: pyqt5
Requires-Dist: pyqtgraph
Requires-Dist: pyqtdarktheme
